aiodataloader/__init__.py
aiodataloader/py.typed
aiodataloader-0.3.0.dist-info/METADATA
aiodataloader-0.3.0.dist-info/WHEEL
aiodataloader-0.3.0.dist-info/licenses/LICENSE
aiodataloader-0.3.0.dist-info/RECORD
