Metadata-Version: 2.1
Name: aiodataloader
Version: 0.3.0
Summary: Asyncio DataLoader implementation for Python
Project-URL: Homepage, https://github.com/syrusakbary/aiodataloader
Author-email: Syrus Akbary <me@syrusakbary.com>
License-File: LICENSE
Keywords: aiodataloader,concurrent,deferred,future
Classifier: Development Status :: 5 - Production/Stable
Classifier: Intended Audience :: Developers
Classifier: License :: OSI Approved :: MIT License
Classifier: Programming Language :: Python :: 3
Classifier: Programming Language :: Python :: 3.6
Classifier: Programming Language :: Python :: 3.7
Classifier: Programming Language :: Python :: 3.8
Classifier: Programming Language :: Python :: 3.9
Classifier: Programming Language :: Python :: 3.10
Classifier: Programming Language :: Python :: 3.11
Classifier: Topic :: Software Development :: Libraries
Requires-Python: >=3.6
Requires-Dist: typing-extensions>=4.1.1
Provides-Extra: lint
Requires-Dist: black; extra == 'lint'
Requires-Dist: flake8; extra == 'lint'
Requires-Dist: flake8-import-order; extra == 'lint'
Requires-Dist: mypy; extra == 'lint'
Provides-Extra: test
Requires-Dist: coveralls; extra == 'test'
Requires-Dist: mock; extra == 'test'
Requires-Dist: pytest-asyncio; extra == 'test'
Requires-Dist: pytest-cov; extra == 'test'
Requires-Dist: pytest>=3.6; extra == 'test'
